hypergate/__init__.py
hypergate-0.0.0.dist-info/LICENSE
hypergate-0.0.0.dist-info/METADATA
hypergate-0.0.0.dist-info/WHEEL
hypergate-0.0.0.dist-info/top_level.txt
hypergate-0.0.0.dist-info/RECORD
