Metadata-Version: 2.1
Name: hypergate
Version: 0.0.0
Summary: Coming soon
Author-email: Matthias Schuff <matthias.schuff@dlr.de>
License-File: LICENSE
